admin_tools/__init__.py
admin_tools/authentication_handler.py
admin_tools/book.py
admin_tools/poem.py
admin_tools/section.py
admin_tools/user.py
connectors/__init__.py
connectors/book.py
connectors/poem.py
connectors/section.py
connectors/tools.py
tools/OUTLIERS.csv
tools/STOPWORDS.txt
tools/__init__.py
tools/api.py
tools/formatter.py
tools/rhyme.py
tools/syllable.py
Augmented_Criticism_Lab_Toolkit-1.1.9.dist-info/LICENSE.txt
Augmented_Criticism_Lab_Toolkit-1.1.9.dist-info/METADATA
Augmented_Criticism_Lab_Toolkit-1.1.9.dist-info/WHEEL
Augmented_Criticism_Lab_Toolkit-1.1.9.dist-info/top_level.txt
Augmented_Criticism_Lab_Toolkit-1.1.9.dist-info/RECORD
